{
    "Ar36": {
        "error": 0.0002514257343083801,
        "error_type": "",
        "fit": "previous",
        "references": [
            {
                "exclude": false,
                "record_id": "bc-03-F-403"
            }
        ],
        "value": 0.00472931349131008
    },
    "Ar37": {
        "error": 0.014218841875597868,
        "error_type": "",
        "fit": "previous",
        "references": [
            {
                "exclude": false,
                "record_id": "bc-03-F-403"
            }
        ],
        "value": 0.03156959734318135
    },
    "Ar38": {
        "error": 0.02661902739678924,
        "error_type": "",
        "fit": "previous",
        "references": [
            {
                "exclude": false,
                "record_id": "bc-03-F-403"
            }
        ],
        "value": -0.024420653629126265
    },
    "Ar39": {
        "error": 0.013709059125430814,
        "error_type": "",
        "fit": "previous",
        "references": [
            {
                "exclude": false,
                "record_id": "bc-03-F-403"
            }
        ],
        "value": -0.0022337752047103393
    },
    "Ar40": {
        "error": 0.025374847857640156,
        "error_type": "",
        "fit": "previous",
        "references": [
            {
                "exclude": false,
                "record_id": "bc-03-F-403"
            }
        ],
        "value": 0.10951508690967282
    }
}